valframe/__init__.py
valframe/valframe.py
valframe-0.0.1.0.dist-info/licenses/LICENSE
valframe-0.0.1.0.dist-info/METADATA
valframe-0.0.1.0.dist-info/WHEEL
valframe-0.0.1.0.dist-info/top_level.txt
valframe-0.0.1.0.dist-info/RECORD
