Metadata-Version: 2.4
Name: valframe
Version: 0.0.1.0
Summary: Create validation classes for your data
Author-email: Leon Luithlen <leontimnaluithlen@gmail.com>
License: BSD 3-Clause
Project-URL: Homepage, https://github.com/0xideas/valframe
Project-URL: Repository, https://github.com/0xideas/valframe
Keywords: data validation,data quality,pandas,polars,dataframe
Requires-Python: >=3.10
License-File: LICENSE
Requires-Dist: polars<2.0,>=1.31.0
Requires-Dist: numpy>=2.0.0
Requires-Dist: pandas>=2.0.0
Requires-Dist: pandera[polars]>=0.18.0
Requires-Dist: beartype
Provides-Extra: test
Requires-Dist: pytest<8.0,>=7.2; extra == "test"
Dynamic: license-file
